LICENSE
setup.py
src/KTC_API.egg-info/PKG-INFO
src/KTC_API.egg-info/SOURCES.txt
src/KTC_API.egg-info/dependency_links.txt
src/KTC_API.egg-info/requires.txt
src/KTC_API.egg-info/top_level.txt
src/ktc_api/__init__.py
src/ktc_api/aio.py
src/ktc_api/types.py